makima/__init__.py
tests/test_makima.py
pymakima-0.1.1.dist-info/LICENSE.md
pymakima-0.1.1.dist-info/METADATA
pymakima-0.1.1.dist-info/WHEEL
pymakima-0.1.1.dist-info/entry_points.txt
pymakima-0.1.1.dist-info/top_level.txt
pymakima-0.1.1.dist-info/RECORD
