Metadata-Version: 2.1
Name: pymakima
Version: 0.1.1
Summary: Asynchronous DNS Brute Forcer by irisdotsh
Home-page: https://github.com/irisdotsh/makima
Author: Iris Blankenship
Author-email: Iris Blankenship <iris@netwatchr.com>
License: # GNU GENERAL PUBLIC LICENSE
Project-URL: Homepage, https://github.com/irisdotsh/makima
Project-URL: Bug Tracker, https://github.com/irisdotsh/makima/issues
Keywords: makima,async,dns,brute,force,security
Classifier: Programming Language :: Python :: 3.11
Classifier: License :: OSI Approved :: GNU General Public License v3 (GPLv3)
Classifier: Topic :: Security
Requires-Python: >=3.11
License-File: LICENSE.md
Requires-Dist: aiodns
Requires-Dist: aiofiles
